README.md
setup.cfg
setup.py
distributions/Binomialdistribution.py
distributions/Gaussiandistribution.py
distributions/Generaldistribution.py
distributions/__init__.py
gausandbinom_distributions.egg-info/PKG-INFO
gausandbinom_distributions.egg-info/SOURCES.txt
gausandbinom_distributions.egg-info/dependency_links.txt
gausandbinom_distributions.egg-info/not-zip-safe
gausandbinom_distributions.egg-info/top_level.txt